app/__init__.py
app/ammo.py
app/armor.py
app/gun.py
app/tank.py
bb_krl_Tank_Battle-1.0.0.dist-info/METADATA
bb_krl_Tank_Battle-1.0.0.dist-info/WHEEL
bb_krl_Tank_Battle-1.0.0.dist-info/top_level.txt
bb_krl_Tank_Battle-1.0.0.dist-info/RECORD
