Metadata-Version: 2.1
Name: bb-krl-Tank-Battle
Version: 1.0.0
Summary: package for consol tank battle
Home-page: https://github.com/bbkrl/TMS_homework
Author: bb_krl
Author-email: bagushevich2003@mail.ru
License: UNKNOWN
Platform: UNKNOWN
